daemo/__init__.py
daemo/api.py
daemo/auth.py
daemo/channel.py
daemo/client.py
daemo/client_factory.py
daemo/constants.py
daemo/errors.py
daemo/exceptions.py
daemo/logging.conf
daemo/protocol.py
daemo/rest.py
daemo/router.py
daemo/storage.py
daemo/utils.py
daemo_api_client-1.0.10.dist-info/DESCRIPTION.rst
daemo_api_client-1.0.10.dist-info/METADATA
daemo_api_client-1.0.10.dist-info/RECORD
daemo_api_client-1.0.10.dist-info/WHEEL
daemo_api_client-1.0.10.dist-info/metadata.json
daemo_api_client-1.0.10.dist-info/top_level.txt
