Metadata-Version: 2.0
Name: daemo-api-client
Version: 1.0.10
Summary: Python API Client for Daemo
Home-page: https://github.com/crowdresearch/daemo-api-client/
Author: Daemo
Author-email: daemo@cs.stanford.edu
License: MIT
Keywords: daemo crowdsourcing client
Platform: UNKNOWN
Requires-Dist: autobahn[twisted] (==0.17.1)
Requires-Dist: pyOpenSSL (==16.1.0)
Requires-Dist: pyyaml (==3.12)
Requires-Dist: rainbow-logging-handler (==2.2.2)
Requires-Dist: requests (==2.11.1)
Requires-Dist: service-identity (==16.0.0)
